et_ppmdcommon.py
et_ppmdcommon-0.4.0.dist-info/entry_points.txt
et_ppmdcommon-0.4.0.dist-info/LICENSE
et_ppmdcommon-0.4.0.dist-info/WHEEL
et_ppmdcommon-0.4.0.dist-info/METADATA
et_ppmdcommon-0.4.0.dist-info/RECORD
