Metadata-Version: 2.1
Name: et-ppmdcommon
Version: 0.4.0
Summary: Tools for the Parallel Programming Course project 2021.
Home-page: https://github.com/etijskens/et_ppMDcommon
License: MIT
Keywords: packaging,poetry
Author: Bert Tijskens
Author-email: engelbert.tijskens@uantwerpen.be
Requires-Python: >=3.7,<4.0
Classifier: License :: OSI Approved :: MIT License
Classifier: Programming Language :: Python :: 3
Classifier: Programming Language :: Python :: 3.7
Classifier: Programming Language :: Python :: 3.8
Classifier: Programming Language :: Python :: 3.9
Requires-Dist: matplotlib (>=3.3.4,<4.0.0)
Requires-Dist: numpy (>=1.20.1,<2.0.0)
Project-URL: Repository, https://github.com/etijskens/et_ppMDcommon
